[
  {
    "title": "Meaning of Aham Brahmasmi — Swadharma",
    "slug": "aham-brahmasmi-meaning",
    "url": "q/aham-brahmasmi-meaning.html",
    "lang": "en",
    "date": "",
    "excerpt": "",
    "tags": ""
  },
  {
    "title": "Authority of the Vedas — Swadharma",
    "slug": "authority-of-the-vedas",
    "url": "q/authority-of-the-vedas.html",
    "lang": "en",
    "date": "",
    "excerpt": "",
    "tags": ""
  },
  {
    "title": "How Old is Sanskrit? — Swadharma",
    "slug": "how-old-is-sanskrit",
    "url": "q/how-old-is-sanskrit.html",
    "lang": "en",
    "date": "",
    "excerpt": "",
    "tags": ""
  },
  {
    "title": "Purpose of Sandhyavandanam — Swadharma",
    "slug": "purpose-of-sandhyavandanam",
    "url": "q/purpose-of-sandhyavandanam.html",
    "lang": "en",
    "date": "",
    "excerpt": "",
    "tags": ""
  },
  {
    "title": "Shruti vs Smriti — Swadharma",
    "slug": "shruti-vs-smriti",
    "url": "q/shruti-vs-smriti.html",
    "lang": "en",
    "date": "",
    "excerpt": "",
    "tags": ""
  },
  {
    "title": "What are the Vedangas? — Swadharma",
    "slug": "what-are-vedangas",
    "url": "q/what-are-vedangas.html",
    "lang": "en",
    "date": "",
    "excerpt": "",
    "tags": ""
  },
  {
    "title": "What is Dharma? — Swadharma",
    "slug": "what-is-dharma",
    "url": "q/what-is-dharma.html",
    "lang": "en",
    "date": "",
    "excerpt": "",
    "tags": ""
  },
  {
    "title": "What is Sanatana Dharma? — Swadharma",
    "slug": "what-is-sanatana-dharma",
    "url": "q/what-is-sanatana-dharma.html",
    "lang": "en",
    "date": "",
    "excerpt": "",
    "tags": ""
  },
  {
    "title": "Who is a Brahmana? — Swadharma",
    "slug": "who-is-brahmana-in-scriptures",
    "url": "q/who-is-brahmana-in-scriptures.html",
    "lang": "en",
    "date": "",
    "excerpt": "",
    "tags": ""
  },
  {
    "title": "Why Many Gods in Hinduism? — Swadharma",
    "slug": "why-many-gods-in-hinduism",
    "url": "q/why-many-gods-in-hinduism.html",
    "lang": "en",
    "date": "",
    "excerpt": "",
    "tags": ""
  },
  {
    "title": ".!58721!._Aham Brahmasmi Meaning",
    "slug": ".!58721!._aham-brahmasmi-meaning",
    "url": "q/.!58721!._aham-brahmasmi-meaning.html",
    "lang": "en",
    "date": "",
    "excerpt": "",
    "tags": ""
  },
  {
    "title": ".!58723!._Authority Of The Vedas",
    "slug": ".!58723!._authority-of-the-vedas",
    "url": "q/.!58723!._authority-of-the-vedas.html",
    "lang": "en",
    "date": "",
    "excerpt": "",
    "tags": ""
  },
  {
    "title": ".!58725!._How Old Is Sanskrit",
    "slug": ".!58725!._how-old-is-sanskrit",
    "url": "q/.!58725!._how-old-is-sanskrit.html",
    "lang": "en",
    "date": "",
    "excerpt": "",
    "tags": ""
  },
  {
    "title": ".!58727!._Purpose Of Sandhyavandanam",
    "slug": ".!58727!._purpose-of-sandhyavandanam",
    "url": "q/.!58727!._purpose-of-sandhyavandanam.html",
    "lang": "en",
    "date": "",
    "excerpt": "",
    "tags": ""
  },
  {
    "title": ".!58729!._Shruti Vs Smriti",
    "slug": ".!58729!._shruti-vs-smriti",
    "url": "q/.!58729!._shruti-vs-smriti.html",
    "lang": "en",
    "date": "",
    "excerpt": "",
    "tags": ""
  },
  {
    "title": ".!58731!._What Are Vedangas",
    "slug": ".!58731!._what-are-vedangas",
    "url": "q/.!58731!._what-are-vedangas.html",
    "lang": "en",
    "date": "",
    "excerpt": "",
    "tags": ""
  },
  {
    "title": ".!58733!._What Is Dharma",
    "slug": ".!58733!._what-is-dharma",
    "url": "q/.!58733!._what-is-dharma.html",
    "lang": "en",
    "date": "",
    "excerpt": "",
    "tags": ""
  },
  {
    "title": ".!58735!._What Is Sanatana Dharma",
    "slug": ".!58735!._what-is-sanatana-dharma",
    "url": "q/.!58735!._what-is-sanatana-dharma.html",
    "lang": "en",
    "date": "",
    "excerpt": "",
    "tags": ""
  },
  {
    "title": ".!58737!._Who Is Brahmana In Scriptures",
    "slug": ".!58737!._who-is-brahmana-in-scriptures",
    "url": "q/.!58737!._who-is-brahmana-in-scriptures.html",
    "lang": "en",
    "date": "",
    "excerpt": "",
    "tags": ""
  },
  {
    "title": ".!58739!._Why Many Gods In Hinduism",
    "slug": ".!58739!._why-many-gods-in-hinduism",
    "url": "q/.!58739!._why-many-gods-in-hinduism.html",
    "lang": "en",
    "date": "",
    "excerpt": "",
    "tags": ""
  }
]